<Zilox>

<append xpath="//vehicle[starts-with(@name,'vehicle')]">
	<property name="impactParticle" value="#@modfolder:Resources/Particles.unity3d?EnergyExplosion"/>
	<property name="impactParticleSound" value="explosion_plasma_small"/>	
</append>

<append xpath="/vehicles">

	<vehicle name="vehicleMuscleCar">

		<property name="cameraDistance" value="5.5, 7"/>
		<property name="cameraTurnRate" value=".2, .35"/>
		<property name="upAngleMax" value="70"/>
		<property name="upForce" value="1"/>
		<property name="steerAngleMax" value="32"/>
		<property name="steerRate" value="130"/>
		<property name="steerCenteringRate" value="90"/>
		<property name="tiltAngleMax" value="80"/>
		<property name="tiltThreshold" value="3"/>
		<property name="tiltDampening" value=".22"/>
		<property name="tiltDampenThreshold" value="8"/>
		<property name="tiltUpForce" value="0"/>
		
		<property name="motorTorque_turbo" value="3500, 1500, 4500, 2000"/>
		<property name="velocityMax_turbo" value="18, 12, 22, 14"/>
		<property name="brakeTorque" value="6000"/>
		<property name="unstickForce" value="1"/>
		<property name="waterDrag_y_velScale_velMaxScale" value="1.8, .9, .1"/>
		<property name="wheelPtlScale" value="1"/>		
		
		<property name="impactParticle" value="#@modfolder:Resources/Particles.unity3d?EnergyExplosion"/>
		<property name="impactParticleSound" value="explosion_plasma_small"/>		

		<property name="hornSound" value="suv_horn"/>

		<property name="recipeName" value="vehicleMuscleCarPlaceable"/>

		<property class="chassis">
			<property name="class" value="Chassis"/>
			<property name="paint" value="car_mesh"/>
		</property>

		<property class="engine">
			<property name="class" value="Engine"/>
			<property name="particleOn" value="Particles/p_on"/>
			<property name="particleBroken" value="Particles/p_broken"/>			
			<property name="fuelKmPerL" value=".1"/>
			<property name="foodDrain" value=".002,.00811"/><!-- driving/turbo, truck -->
			<property name="gear1" value="
								500,2500, -1400,800,0, 700,2200,900,
								Vehicles/Suv/suv_accel1,
								Vehicles/Suv/suv_decel1,
								0, .7, 1, .1, -9, .12, .1, Vehicles/Suv/suv_idle_lp,
								-.4, -.02, .7, .7, -.2, 9, .2, Vehicles/Suv/suv_max_speed_lp
								"/>
			<property name="gear2" value="
								500,2500, -2000,1000,2000, 600,2200,800,
								Vehicles/Suv/suv_accel2,
								Vehicles/Suv/suv_decel1,
								-.25, -.05, .2, .4, -1, 1, .1, Vehicles/Suv/suv_max_speed_lp
								"/>
			<property name="gear3" value="
								500,2500, -2000,1000,2000, 500,2200,1000,
								Vehicles/Suv/suv_accel3,
								Vehicles/Suv/suv_decel2,
								-.28, -.07, .3, .6, -1, 1, .1, Vehicles/Suv/suv_max_speed_lp
								"/>
			<property name="gear4" value="
								500,2500, -2000,1000,2000, 500,9999,9999,
								,
								Vehicles/Suv/suv_decel2,
								-.31, -.08, .6, .9, -1, 1, .1, Vehicles/Suv/suv_max_speed_lp
								"/>
			<property name="sound_start" value="Vehicles/Suv/suv_startup"/>
			<property name="sound_shut_off" value="Vehicles/Suv/suv_shutoff"/>
			<property name="sound_no_fuel_shut_off" value="Vehicles/Motorbike/motorbike_empty"/>
		</property>

		<property class="fuelTank">
			<property name="class" value="FuelTank"/>
			<property name="capacity" value="350"/>
		</property>

		<property class="handlebars">
			<property name="class" value="Steering"/>
			<property name="transform" value="Origin/steering_joint"/>
			<property name="steerAngle" value="0, 0, -60"/>
			<property name="IKHandLPosition" value="-.2596, -.03777, -.266483"/>
			<property name="IKHandLRotation" value="-65.88229, 166.2278, -67.5802"/>
			<property name="IKHandRPosition" value=".24465, -.0909, -.25648"/>
			<property name="IKHandRRotation" value="54.6357, 14.0615, 102.1651"/>
		</property>

		<property class="seat0">
			<property name="class" value="Seat"/>
			<property name="pose" value="40"/>			
			<property name="position" value="-.2, -.57, .5"/> <!-- Left/Right, Down/Up, Back/Front -->
			<property name="rotation" value="-25, 0, 0"/>
			<property name="exit" value="-1.6,0,0 ~ 1.6,0,-1 ~ -.4,0,-2.8 ~ -.4,0,2.6 ~ -.4,2.1,0"/>
			<property name="IKFootLPosition" value="-.34, .9, .37"/>
			<property name="IKFootRPosition" value=".34, .9, .37"/>			
			<property name="IKFootLRotation" value="-30, 0, 0"/>
			<property name="IKFootRRotation" value="-30, 0, 0"/>			
		</property>

		<property class="seat1">
			<property name="class" value="Seat"/>
			<property name="pose" value="41"/>			
			<property name="position" value=".2, -.57, .5"/> <!-- Left/Right, Down/Up, Back/Front -->
			<property name="rotation" value="-25, 0, 0"/>
			<property name="exit" value="1.6,0,0 ~ -1.6,0,-1 ~ .4,0,-2.8 ~ .4,0,2.6 ~ .4,2.1,0"/>
			<property name="IKFootLPosition" value="-.34, .9, .37"/>
			<property name="IKFootRPosition" value=".34, .9, .37"/>			
			<property name="IKFootLRotation" value="-30, 0, 0"/>
			<property name="IKFootRRotation" value="-30, 0, 0"/>		
		</property>

		<property class="wheel0">
			<property name="steerTransform" value="Origin/frontLeftWheelStear_joint"/>
			<property name="tireTransform" value="Origin/frontLeftWheelStear_joint/frontLeftWheel_joint"/>
			<property name="tireSuspensionPercent" value="1"/>
			<property name="torqueScale_motor_brake" value="1, .8"/>
		</property>

		<property class="wheel1">
			<property name="steerTransform" value="Origin/frontRightWheelStear_joint"/>
			<property name="tireTransform" value="Origin/frontRightWheelStear_joint/frontRightWheel_joint"/>
			<property name="tireSuspensionPercent" value="1"/>
			<property name="torqueScale_motor_brake" value="1, .8"/>
		</property>

		<property class="wheel2">
			<property name="tireTransform" value="Origin/backLeftWheelJoint"/>
			<property name="tireSuspensionPercent" value="1"/>
			<property name="torqueScale_motor_brake" value="1, 1"/>
		</property>

		<property class="wheel3">
			<property name="tireTransform" value="Origin/backRightWheelJoint"/>
			<property name="tireSuspensionPercent" value="1"/>
			<property name="torqueScale_motor_brake" value="1, 1"/>
		</property>

		<property class="headlight">
			<property name="class" value="Headlight"/>
			<property name="transform" value="Origin/headlight"/>
			<property name="bright" value=".75"/>			
		</property>

		<property class="storage">
			<property name="class" value="Storage"/>
		</property>

	</vehicle>
	
	<vehicle name="vehiclePickupTruck">

		<property name="cameraDistance" value="5.5, 7"/>
		<property name="cameraTurnRate" value=".2, .35"/>
		<property name="upAngleMax" value="70"/>
		<property name="upForce" value="1"/>
		<property name="steerAngleMax" value="32"/>
		<property name="steerRate" value="130"/>
		<property name="steerCenteringRate" value="90"/>
		<property name="tiltAngleMax" value="80"/>
		<property name="tiltThreshold" value="3"/>
		<property name="tiltDampening" value=".22"/>
		<property name="tiltDampenThreshold" value="8"/>
		<property name="tiltUpForce" value="0"/>
		
		<property name="motorTorque_turbo" value="3500, 1500, 4500, 2000"/>
		<property name="velocityMax_turbo" value="12, 10, 16, 12"/>
		<property name="brakeTorque" value="6000"/>
		<property name="unstickForce" value="1"/>
		<property name="waterDrag_y_velScale_velMaxScale" value="1.8, .9, .1"/>
		<property name="wheelPtlScale" value="1"/>		
		
		<property name="impactParticle" value="#@modfolder:Resources/Particles.unity3d?EnergyExplosion"/>
		<property name="impactParticleSound" value="explosion_plasma_small"/>		

		<property name="hornSound" value="suv_horn"/>

		<property name="recipeName" value="vehiclePickupTruckPlaceable"/>

		<property class="chassis">
			<property name="class" value="Chassis"/>
			<property name="paint" value="car_mesh"/>
		</property>

		<property class="engine">
			<property name="class" value="Engine"/>
			<property name="particleBroken" value="Particles/p_broken"/>			
			<property name="fuelKmPerL" value=".1"/>
			<property name="foodDrain" value=".002,.00811"/><!-- driving/turbo, truck -->
			<property name="gear1" value="
								500,2500, -1400,800,0, 700,2200,900,
								Vehicles/Suv/suv_accel1,
								Vehicles/Suv/suv_decel1,
								0, .7, 1, .1, -9, .12, .1, Vehicles/Suv/suv_idle_lp,
								-.4, -.02, .7, .7, -.2, 9, .2, Vehicles/Suv/suv_max_speed_lp
								"/>
			<property name="gear2" value="
								500,2500, -2000,1000,2000, 600,2200,800,
								Vehicles/Suv/suv_accel2,
								Vehicles/Suv/suv_decel1,
								-.25, -.05, .2, .4, -1, 1, .1, Vehicles/Suv/suv_max_speed_lp
								"/>
			<property name="gear3" value="
								500,2500, -2000,1000,2000, 500,2200,1000,
								Vehicles/Suv/suv_accel3,
								Vehicles/Suv/suv_decel2,
								-.28, -.07, .3, .6, -1, 1, .1, Vehicles/Suv/suv_max_speed_lp
								"/>
			<property name="gear4" value="
								500,2500, -2000,1000,2000, 500,9999,9999,
								,
								Vehicles/Suv/suv_decel2,
								-.31, -.08, .6, .9, -1, 1, .1, Vehicles/Suv/suv_max_speed_lp
								"/>
			<property name="sound_start" value="Vehicles/Suv/suv_startup"/>
			<property name="sound_shut_off" value="Vehicles/Suv/suv_shutoff"/>
			<property name="sound_no_fuel_shut_off" value="Vehicles/Motorbike/motorbike_empty"/>
		</property>

		<property class="fuelTank">
			<property name="class" value="FuelTank"/>
			<property name="capacity" value="400"/>
		</property>

		<property class="handlebars">
			<property name="class" value="Steering"/>
			<property name="transform" value="Origin/steering_joint"/>
			<property name="steerAngle" value="0, 0, -60"/>
			<property name="IKHandLPosition" value="-.2596, -.03777, -.266483"/>
			<property name="IKHandLRotation" value="-65.88229, 166.2278, -67.5802"/>
			<property name="IKHandRPosition" value=".24465, -.0909, -.25648"/>
			<property name="IKHandRRotation" value="54.6357, 14.0615, 102.1651"/>
		</property>

		<property class="seat0">
			<property name="class" value="Seat"/> 
			<property name="pose" value="40"/>			
			<property name="position" value="-.2, 0, .8"/> <!-- Left/Right, Down/Up, Back/Front -->
			<property name="rotation" value="-25, 0, 0"/>
			<property name="exit" value="-1.6,0,0 ~ 1.6,0,-1 ~ -.4,0,-2.8 ~ -.4,0,2.6 ~ -.4,2.1,0"/>
			<property name="IKFootLPosition" value="-.1, .5, .37"/>
			<property name="IKFootLRotation" value="-30, 0, 0"/>
			<property name="IKFootRPosition" value=".1, .5, .37"/>
			<property name="IKFootRRotation" value="-30, 0, 0"/>			
		</property>

		<property class="seat1">
			<property name="class" value="Seat"/>
			<property name="pose" value="41"/>			
			<property name="position" value=".4, 0, .8"/>
			<property name="rotation" value="-27, 0, 0"/>
			<property name="exit" value="1.6,0,0 ~ -1.6,0,-1 ~ .4,0,-2.8 ~ .4,0,2.6 ~ .4,2.1,0"/>
			<property name="IKFootLPosition" value="-.1, .5, .37"/>
			<property name="IKFootLRotation" value="-30, 0, 0"/>
			<property name="IKFootRPosition" value=".1, .5, .37"/>
			<property name="IKFootRRotation" value="-30, 0, 0"/>		
		</property>

		<property class="seat2">
			<property name="class" value="Seat"/>
			<property name="pose" value="42"/>		
			<property name="position" value="-.1, .53, -1.6"/>
			<property name="rotation" value="-33, 90, 0"/>
			<property name="exit" value="-.8,0,-3 ~ -1.6,0,-3 ~ 1.6,0,-2 ~ -.5,0,-2.8 ~ -.5,0,2.6 ~ -.4,2.1,-1"/>
			<property name="mod" value="1"/>
		</property>

		<property class="seat3">
			<property name="class" value="Seat"/>
			<property name="pose" value="43"/>			
			<property name="position" value=".25, .53, -1.6"/>
			<property name="rotation" value="-33, -90, 0"/>
			<property name="exit" value=".8,0,-3 ~ -1.6,0,-3 ~ 1.6,0,-2 ~ -.5,0,-2.8 ~ -.5,0,2.6 ~ -.4,2.1,-1"/>
			<property name="mod" value="1"/>
		</property>

		<property class="wheel0">
			<property name="steerTransform" value="Origin/frontLeftWheelStear_joint"/>
			<property name="tireTransform" value="Origin/frontLeftWheelStear_joint/frontLeftWheel_joint"/>
			<property name="tireSuspensionPercent" value="1"/>
			<property name="torqueScale_motor_brake" value="1, .8"/>
		</property>

		<property class="wheel1">
			<property name="steerTransform" value="Origin/frontRightWheelStear_joint"/>
			<property name="tireTransform" value="Origin/frontRightWheelStear_joint/frontRightWheel_joint"/>
			<property name="tireSuspensionPercent" value="1"/>
			<property name="torqueScale_motor_brake" value="1, .8"/>
		</property>

		<property class="wheel2">
			<property name="tireTransform" value="Origin/backLeftWheelJoint"/>
			<property name="tireSuspensionPercent" value="1"/>
			<property name="torqueScale_motor_brake" value="1, 1"/>
		</property>

		<property class="wheel3">
			<property name="tireTransform" value="Origin/backRightWheelJoint"/>
			<property name="tireSuspensionPercent" value="1"/>
			<property name="torqueScale_motor_brake" value="1, 1"/>
		</property>

		<property class="headlight">
			<property name="class" value="Headlight"/>
			<property name="transform" value="Origin/headlight"/>
			<property name="bright" value=".75"/>
		</property>

		<property class="storage">
			<property name="class" value="Storage"/>
		</property>

	</vehicle>

	<vehicle name="vehicleLuxurySedan">

		<property name="cameraDistance" value="5.5, 7"/>
		<property name="cameraTurnRate" value=".2, .35"/>
		<property name="upAngleMax" value="70"/>
		<property name="upForce" value="1"/>
		<property name="steerAngleMax" value="32"/>
		<property name="steerRate" value="130"/>
		<property name="steerCenteringRate" value="90"/>
		<property name="tiltAngleMax" value="80"/>
		<property name="tiltThreshold" value="3"/>
		<property name="tiltDampening" value=".22"/>
		<property name="tiltDampenThreshold" value="8"/>
		<property name="tiltUpForce" value="0"/>
		
		<property name="motorTorque_turbo" value="3500, 1500, 4500, 2000"/>
		<property name="velocityMax_turbo" value="14, 12, 18, 14"/>
		<property name="brakeTorque" value="6000"/>
		<property name="unstickForce" value="1"/>
		<property name="waterDrag_y_velScale_velMaxScale" value="1.8, .9, .1"/>
		<property name="wheelPtlScale" value="1"/>		
		
		<property name="impactParticle" value="#@modfolder:Resources/Particles.unity3d?EnergyExplosion"/>
		<property name="impactParticleSound" value="explosion_plasma_small"/>		

		<property name="hornSound" value="suv_horn"/>

		<property name="recipeName" value="vehicleLuxurySedanPlaceable"/>

		<property class="chassis">
			<property name="class" value="Chassis"/>
			<property name="paint" value="car_mesh"/>
		</property>

		<property class="engine">
			<property name="class" value="Engine"/>
			<property name="fuelKmPerL" value=".1"/>
			<property name="foodDrain" value=".002,.00811"/><!-- driving/turbo, truck -->
			<property name="gear1" value="
								500,2500, -1400,800,0, 700,2200,900,
								Vehicles/Suv/suv_accel1,
								Vehicles/Suv/suv_decel1,
								0, .7, 1, .1, -9, .12, .1, Vehicles/Suv/suv_idle_lp,
								-.4, -.02, .7, .7, -.2, 9, .2, Vehicles/Suv/suv_max_speed_lp
								"/>
			<property name="gear2" value="
								500,2500, -2000,1000,2000, 600,2200,800,
								Vehicles/Suv/suv_accel2,
								Vehicles/Suv/suv_decel1,
								-.25, -.05, .2, .4, -1, 1, .1, Vehicles/Suv/suv_max_speed_lp
								"/>
			<property name="gear3" value="
								500,2500, -2000,1000,2000, 500,2200,1000,
								Vehicles/Suv/suv_accel3,
								Vehicles/Suv/suv_decel2,
								-.28, -.07, .3, .6, -1, 1, .1, Vehicles/Suv/suv_max_speed_lp
								"/>
			<property name="gear4" value="
								500,2500, -2000,1000,2000, 500,9999,9999,
								,
								Vehicles/Suv/suv_decel2,
								-.31, -.08, .6, .9, -1, 1, .1, Vehicles/Suv/suv_max_speed_lp
								"/>
			<property name="sound_start" value="Vehicles/Suv/suv_startup"/>
			<property name="sound_shut_off" value="Vehicles/Suv/suv_shutoff"/>
			<property name="sound_no_fuel_shut_off" value="Vehicles/Motorbike/motorbike_empty"/>
		</property>

		<property class="fuelTank">
			<property name="class" value="FuelTank"/>
			<property name="capacity" value="400"/>
		</property>

		<property class="handlebars">
			<property name="class" value="Steering"/>
			<property name="transform" value="Origin/steering_joint"/>
			<property name="steerAngle" value="0, 0, -60"/>
			<property name="IKHandLPosition" value="-.2596, -.03777, -.266483"/>
			<property name="IKHandLRotation" value="-65.88229, 166.2278, -67.5802"/>
			<property name="IKHandRPosition" value=".24465, -.0909, -.25648"/>
			<property name="IKHandRRotation" value="54.6357, 14.0615, 102.1651"/>
		</property>

		<property class="seat0">
			<property name="class" value="Seat"/>
			<property name="pose" value="40"/>			
			<property name="position" value="-.3, -.55, .5"/>
			<property name="rotation" value="-25, 0, 0"/>
			<property name="exit" value="-1.6,0,0 ~ 1.6,0,-1 ~ -.4,0,-2.8 ~ -.4,0,2.6 ~ -.4,2.1,0"/>
			<property name="IKFootLPosition" value="-.34, .8, .37"/>
			<property name="IKFootLRotation" value="-30, 0, 0"/>
			<property name="IKFootRPosition" value=".34, .8, .37"/>
			<property name="IKFootRRotation" value="-30, 0, 0"/>			
		</property>

		<property class="seat1">
			<property name="class" value="Seat"/>
			<property name="pose" value="41"/>			
			<property name="position" value=".3, -.55, .5"/>
			<property name="rotation" value="-27, 0, 0"/>
			<property name="exit" value="1.6,0,0 ~ -1.6,0,-1 ~ .4,0,-2.8 ~ .4,0,2.6 ~ .4,2.1,0"/>
			<property name="IKFootLPosition" value="-.34, .8, .37"/>
			<property name="IKFootLRotation" value="-30, 0, 0"/>
			<property name="IKFootRPosition" value=".34, .8, .37"/>
			<property name="IKFootRRotation" value="-30, 0, 0"/>			
		</property>

		<property class="seat2">
			<property name="class" value="Seat"/>
			<property name="pose" value="42"/>			
			<property name="position" value="-.3, -.55, -.1"/>
			<property name="rotation" value="-25, 0, 0"/>
			<property name="exit" value="-1.6,0,0 ~ 1.6,0,-1 ~ -.4,0,-2.8 ~ -.4,0,2.6 ~ -.4,2.1,0"/>
			<property name="mod" value="1"/>			
			<property name="IKFootLPosition" value="-.34, .8, .37"/>
			<property name="IKFootLRotation" value="-30, 0, 0"/>
			<property name="IKFootRPosition" value=".34, .8, .37"/>
			<property name="IKFootRRotation" value="-30, 0, 0"/>			
		</property>

		<property class="seat3">
			<property name="class" value="Seat"/>
			<property name="pose" value="43"/>			
			<property name="position" value=".3, -.55, -.1"/>
			<property name="rotation" value="-25, 0, 0"/>
			<property name="exit" value="1.6,0,0 ~ -1.6,0,-1 ~ .4,0,-2.8 ~ .4,0,2.6 ~ .4,2.1,0"/>
			<property name="mod" value="1"/>
			<property name="IKFootLPosition" value="-.34, .8, .37"/>
			<property name="IKFootLRotation" value="-30, 0, 0"/>
			<property name="IKFootRPosition" value=".34, .8, .37"/>
			<property name="IKFootRRotation" value="-30, 0, 0"/>			
		</property>

		<property class="wheel0">
			<property name="steerTransform" value="Origin/frontLeftWheelStear_joint"/>
			<property name="tireTransform" value="Origin/frontLeftWheelStear_joint/frontLeftWheel_joint"/>
			<property name="tireSuspensionPercent" value="1"/>
			<property name="torqueScale_motor_brake" value="1, .8"/>
		</property>

		<property class="wheel1">
			<property name="steerTransform" value="Origin/frontRightWheelStear_joint"/>
			<property name="tireTransform" value="Origin/frontRightWheelStear_joint/frontRightWheel_joint"/>
			<property name="tireSuspensionPercent" value="1"/>
			<property name="torqueScale_motor_brake" value="1, .8"/>
		</property>

		<property class="wheel2">
			<property name="tireTransform" value="Origin/backLeftWheelJoint"/>
			<property name="tireSuspensionPercent" value="1"/>
			<property name="torqueScale_motor_brake" value="1, 1"/>
		</property>

		<property class="wheel3">
			<property name="tireTransform" value="Origin/backRightWheelJoint"/>
			<property name="tireSuspensionPercent" value="1"/>
			<property name="torqueScale_motor_brake" value="1, 1"/>
		</property>

		<property class="headlight">
			<property name="class" value="Headlight"/>
			<property name="transform" value="Origin/headlight"/>
			<property name="bright" value=".75"/>
		</property>

		<property class="storage">
			<property name="class" value="Storage"/>
		</property>

	</vehicle>

	<vehicle name="vehicleHoverCar">
		<property name="cameraDistance" value="3.5, 5"/>
		<property name="cameraTurnRate" value=".2, .35"/>
		<property name="steerRate" value="130"/>
		<property name="steerCenteringRate" value="90"/>

		<property name="tiltAngleMax" value="8"/>
		<property name="tiltThreshold" value="2"/>
		<property name="tiltDampening" value=".01"/>
		<property name="tiltDampenThreshold" value="0"/>
		<property name="tiltUpForce" value="1"/>
		<property name="upAngleMax" value="60"/>
		<property name="upForce" value=".5"/>
		
		<property name="motorTorque_turbo" value="1, 1, 2, 2"/>
		<property name="velocityMax_turbo" value="15, 9, 22, 9"/>
		<property name="brakeTorque" value="10"/>
		<property name="unstickForce" value="1"/>
		<property name="airDrag_velScale_angVelScale" value=".997, .97"/>
		<property name="waterDrag_y_velScale_velMaxScale" value="1.5, .9, 1"/>
		<property name="waterLift_y_depth_force" value="1, .5, .1"/>		
		
		<property name="impactParticle" value="#@modfolder:Resources/Particles.unity3d?EnergyExplosion"/>
		<property name="impactParticleSound" value="explosion_plasma_small"/>		

		<property name="hornSound" value="gyrocopter_horn"/>

		<property name="recipeName" value="vehicleHoverCarPlaceable" />
		
		<property class="chassis">
			<property name="class" value="Chassis"/>
			<property name="paint" value="hovercar"/>
		</property>		

		<property class="engine">
			<property name="class" value="Engine"/>
			<property name="slot_type" value="engine"/>
			<property name="particleOn" value="Particles/p_on"/>		
			<property name="fuelKmPerL" value="0.15"/>
			<property name="foodDrain" value=".002,.00811"/><!-- driving/turbo, gyro -->
			<property name="gear1" value="
								500,2500, -1400,800,0, 1500,9999,9999,
								,
								,
								0, .5,  .45, .1,  -9, .1, .1, hover_engine_lp,
								-.1, .1,  .65, .7,  0, 9, .1, hover_engine_lp
								"/>
			<property name="sound_start" value="hover_startup"/>
			<property name="sound_shut_off" value="hover_shutoff"/>
			<property name="sound_no_fuel_shut_off" value="Vehicles/Gyrocopter/gyrocopter_sputter"/>
			<property name="sound_particle_on" value="hover_engine_thruster_lp"/>				
		</property>

		<property class="fuelTank">
			<property name="class" value="FuelTank"/>
			<property name="capacity" value="500"/>
		</property>

		<property class="handlebars">
			<property name="class" value="Steering"/>
			<property name="steerMaxAngle" value="0"/>
			<property name="IKHandLPosition" value="-0.0781, 1.3623, 0.2236"/>
			<property name="IKHandLRotation" value="-85.6472, -59.8085, 175.7939"/>
			<property name="IKHandRPosition" value="0.0359, 1.4392, 0.2335"/>
			<property name="IKHandRRotation" value="83.2585, 90.3006, -170.2602"/>
		</property>

		<property class="seat0">
			<property name="class" value="Seat"/>
			<property name="pose" value="50"/>			
			<property name="position" value="0, -.2, -.1"/>
			<property name="rotation" value="-45, 0, 0"/>
			<property name="exit" value="-1.6,0,0 ~ 1.6,0,-1 ~ -.4,0,-2.8 ~ -.4,0,2.6 ~ -.4,2.1,0"/>					
		</property>

		<property class="seat1">
			<property name="class" value="Seat"/>
			<property name="pose" value="51"/>			
			<property name="position" value="0, -.2, -.1"/>
			<property name="rotation" value="-45, 0, 0"/>
			<property name="exit" value="1.6,0,0 ~ -1.6,0,-1 ~ .4,0,-2.8 ~ .4,0,2.6 ~ .4,2.1,0"/>
		</property>

		<property class="seat2">
			<property name="class" value="Seat"/>
			<property name="pose" value="52"/>			
			<property name="position" value="0, -.2, -.1"/>
			<property name="rotation" value="-45, 0, 0"/>
			<property name="exit" value="1.6,0,0 ~ -1.6,0,-1 ~ .4,0,-2.8 ~ .4,0,2.6 ~ .4,2.1,0"/>
		</property>

		<property class="seat3">
			<property name="class" value="Seat"/>
			<property name="pose" value="53"/>			
			<property name="position" value="0, -.2, -.1"/>
			<property name="rotation" value="-45, 0, 0"/>
			<property name="exit" value="1.6,0,0 ~ -1.6,0,-1 ~ .4,0,-2.8 ~ .4,0,2.6 ~ .4,2.1,0"/>
		</property>

		<property class="seat4">
			<property name="class" value="Seat"/>
			<property name="pose" value="54"/>			
			<property name="position" value="0, -.2, -.1"/>
			<property name="rotation" value="-45, 0, 0"/>
			<property name="exit" value="1.6,0,0 ~ -1.6,0,-1 ~ .4,0,-2.8 ~ .4,0,2.6 ~ .4,2.1,0"/>
		</property>

		<property class="seat5">
			<property name="class" value="Seat"/>
			<property name="pose" value="55"/>			
			<property name="position" value="0, -.2, -.1"/>
			<property name="rotation" value="-45, 0, 0"/>
			<property name="exit" value="1.6,0,0 ~ -1.6,0,-1 ~ .4,0,-2.8 ~ .4,0,2.6 ~ .4,2.1,0"/>
		</property>

		<property class="seat6">
			<property name="class" value="Seat"/>
			<property name="pose" value="56"/>			
			<property name="position" value="0, -.2, -.1"/>
			<property name="rotation" value="-45, 0, 0"/>
			<property name="exit" value="1.6,0,0 ~ -1.6,0,-1 ~ .4,0,-2.8 ~ .4,0,2.6 ~ .4,2.1,0"/>
		</property>

		<property class="seat7">
			<property name="class" value="Seat"/>
			<property name="pose" value="57"/>			
			<property name="position" value="0, -.2, -.1"/>
			<property name="rotation" value="-45, 0, 0"/>
			<property name="exit" value="1.6,0,0 ~ -1.6,0,-1 ~ .4,0,-2.8 ~ .4,0,2.6 ~ .4,2.1,0"/>
		</property>		

		<property class="motor0">
			<property name="engine" value="engine"/>
			<property name="engineOffPer" value=".02"/>
			<property name="rpmAccel_min_max" value="0.01, .2"/>
			<property name="rpmMax" value="8"/>
			<property name="rpmDrag" value=".993"/>
			<property name="trigger" value="relative"/>
			<property name="type" value="spin"/>
			<property name="transform" value="Origin/TopPropellerJoint"/>
			<property name="axis" value="1"/>
		</property>
		
		<property class="motor1">
			<property name="engine" value="engine"/>
			<property name="turbo" value="1.35"/>
			<property name="rpmAccel_min_max" value="0.01, .1"/>
			<property name="rpmMax" value="8"/>
			<property name="rpmDrag" value=".993"/>
			<property name="trigger" value="relative"/>
			<property name="type" value="spin"/>
			<property name="transform" value="Origin/BackPropellerJoint"/>
			<property name="axis" value="2"/>
		</property>	

		<property class="force0">
			<property name="trigger" value="motor0"/>
			<property name="type" value="relative"/>
			<property name="force" value="0, .195, 0"/>
			<property name="ceiling" value="200, 280"/>
		</property>
		
		<property class="force1">
			<property name="trigger" value="motor1"/>
			<property name="type" value="relative"/>
			<property name="force" value="0, 0,.0"/>
		</property>
		
		<property class="force2">
			<property name="trigger" value="inputForward"/>
			<property name="type" value="relative"/>
			<property name="force" value="0, 0.03,0 "/>
		</property>
		
		<property class="force3">
			<property name="trigger" value="inputStrafe"/>
			<property name="type" value="relativeTorque"/>
			<property name="force" value="0, .02, 0"/>
		</property>
		
		<property class="force4">
			<property name="trigger" value="inputUp"/>
			<property name="type" value="relativeTorque"/>
			<property name="force" value="-.01, 0, 0"/>
		</property>
		
		<property class="force5">
			<property name="trigger" value="inputDown"/>
			<property name="type" value="relativeTorque"/>
			<property name="force" value=".01, 0, 0"/>
		</property>
		
		<property class="headlight">
			<property name="class" value="Headlight"/>
			<property name="transform" value="Origin/headlight"/>
			<property name="bright" value=".75"/>
		</property>	

		<property class="storage">
			<property name="class" value="Storage"/>
		</property>
  </vehicle>

</append>
</Zilox>